{"stats":{"minecraft:crafted":{"minecraft:stick":16,"minecraft:wooden_pickaxe":2,"minecraft:stone_axe":2,"minecraft:oak_planks":36,"minecraft:stone_pickaxe":2,"minecraft:crafting_table":1},"minecraft:custom":{"minecraft:interact_with_crafting_table":7,"minecraft:time_since_rest":3529,"minecraft:walk_one_cm":21357,"minecraft:walk_under_water_one_cm":820,"minecraft:mob_kills":2,"minecraft:damage_taken":450,"minecraft:play_time":12000,"minecraft:damage_dealt":203,"minecraft:jump":331,"minecraft:time_since_death":3505,"minecraft:drop":46,"minecraft:sprint_one_cm":55190,"minecraft:open_chest":1,"minecraft:fall_one_cm":11608,"minecraft:total_world_time":12000,"minecraft:swim_one_cm":6848,"minecraft:fly_one_cm":70581,"minecraft:walk_on_water_one_cm":3753,"minecraft:crouch_one_cm":6280,"minecraft:sneak_time":1923,"minecraft:deaths":2},"minecraft:mined":{"minecraft:short_grass":19,"minecraft:fern":6,"minecraft:oak_leaves":14,"minecraft:dirt":9,"minecraft:crafting_table":1,"minecraft:leaf_litter":11,"minecraft:oak_log":9,"minecraft:grass_block":8,"minecraft:large_fern":24,"minecraft:spruce_leaves":1,"minecraft:iron_ore":2,"minecraft:stone":35},"minecraft:killed":{"minecraft:pig":2},"minecraft:picked_up":{"minecraft:porkchop":6,"minecraft:dirt":28,"minecraft:wooden_pickaxe":1,"minecraft:stick":4,"minecraft:cobblestone":40,"minecraft:oak_planks":9,"minecraft:crafting_table":1,"minecraft:red_mushroom":2,"minecraft:oak_sapling":2,"minecraft:raw_iron":2,"minecraft:leaf_litter":43,"minecraft:oak_log":9,"minecraft:stone_axe":1,"minecraft:wheat_seeds":7,"minecraft:iron_chestplate":1},"minecraft:used":{"minecraft:stone_axe":6,"minecraft:leaf_litter":3,"minecraft:crafting_table":1,"minecraft:iron_chestplate":1,"minecraft:wooden_pickaxe":15,"minecraft:stone_pickaxe":22,"minecraft:dirt":6},"minecraft:killed_by":{"minecraft:skeleton":2},"minecraft:dropped":{"minecraft:cobblestone":19,"minecraft:wheat_seeds":2,"minecraft:leaf_litter":40}},"DataVersion":4440}